novabrawlstars/__init__.py
novabrawlstars/client.py
novabrawlstars/exceptions.py
novabrawlstars/models/__init__.py
novabrawlstars/models/battlelog/__init__.py
novabrawlstars/models/battlelog/battleEventType.py
novabrawlstars/models/battlelog/battleResultType.py
novabrawlstars/models/battlelog/battleTeamsType.py
novabrawlstars/models/battlelog/battlelog.py
novabrawlstars/models/battlelog/brawlerBattleType.py
novabrawlstars/models/battlelog/starPlayerType.py
novabrawlstars/models/brawler/__init__.py
novabrawlstars/models/brawler/brawlerType.py
novabrawlstars/models/club/__init__.py
novabrawlstars/models/club/club.py
novabrawlstars/models/club/clubMember.py
novabrawlstars/models/club/clubMemberArgs.py
novabrawlstars/models/paging/__init__.py
novabrawlstars/models/paging/pagingType.py
novabrawlstars/models/player/__init__.py
novabrawlstars/models/player/brawlerAccessoryType.py
novabrawlstars/models/player/brawlerGearStatsType.py
novabrawlstars/models/player/brawlerStarPowerType.py
novabrawlstars/models/player/brawlerStatsType.py
novabrawlstars/models/player/player.py
novabrawlstars/models/player/playerClubType.py
novabrawlstars/models/player/playerIconType.py
novabrawlstars/models/ranking/__init__.py
novabrawlstars/models/ranking/brawlerRankingCountryType.py
novabrawlstars/models/ranking/brawlerRankingType.py
novabrawlstars/models/ranking/clubRankingCountryType.py
novabrawlstars/models/ranking/clubRankingType.py
novabrawlstars/models/ranking/playerRankingCountryType.py
novabrawlstars/models/ranking/playerRankingType.py
novabrawlstars-0.1.9.dist-info/licenses/LICENSE
novabrawlstars-0.1.9.dist-info/METADATA
novabrawlstars-0.1.9.dist-info/WHEEL
novabrawlstars-0.1.9.dist-info/top_level.txt
novabrawlstars-0.1.9.dist-info/RECORD
