Metadata-Version: 2.4
Name: novabrawlstars
Version: 0.1.9
Summary: Unofficial Python wrapper for the Brawl Stars API.
Home-page: https://github.com/NovaFenice/NovaBrawlStarsAPI
Author: NovaFenice
License: MIT
Keywords: brawl stars,api,brawlstars,brawlstars
Classifier: Programming Language :: Python :: 3
Classifier: License :: OSI Approved :: MIT License
Classifier: Operating System :: OS Independent
Requires-Python: >=3.8
License-File: LICENSE
Requires-Dist: httpx
Requires-Dist: asyncio
Dynamic: author
Dynamic: classifier
Dynamic: description
Dynamic: description-content-type
Dynamic: home-page
Dynamic: keywords
Dynamic: license
Dynamic: license-file
Dynamic: requires-dist
Dynamic: requires-python
Dynamic: summary
